LICENSE
README.md
setup.py
scripts/ultisnips2vscode
test/test_ultisnips_parser.py
ultisnips2vscode/UltisnipParser.py
ultisnips2vscode/__init__.py
ultisnips2vscode/vscode_filetypes.py
ultisnips_vscode.egg-info/PKG-INFO
ultisnips_vscode.egg-info/SOURCES.txt
ultisnips_vscode.egg-info/dependency_links.txt
ultisnips_vscode.egg-info/top_level.txt