Metadata-Version: 2.1
Name: ultisnips-vscode
Version: 1.2
Summary: Converts a directory of ultisnips snippets to json for vscode
Home-page: https://github.com/erietz/ultisnips-vscode
Author: Ethan Rietz
Author-email: ewrietz@gmail.com
License: UNKNOWN
Keywords: vim ultisnips snippets vscode json
Platform: UNKNOWN
License-File: LICENSE
